README.md
setup.py
itanium_demangler/__init__.py
itanium_demangler.egg-info/PKG-INFO
itanium_demangler.egg-info/SOURCES.txt
itanium_demangler.egg-info/dependency_links.txt
itanium_demangler.egg-info/top_level.txt