Metadata-Version: 2.1
Name: itanium_demangler
Version: 1.0
Summary: Pure Python parser for mangled itanium symbols
Home-page: https://github.com/whitequark/python-itanium_demangler
Author: whitequark
Author-email: whitequark@whitequark.org
License: UNKNOWN
Platform: UNKNOWN
Classifier: Programming Language :: Python :: 3
Classifier: Programming Language :: Python :: 2
Classifier: Operating System :: OS Independent
